github_dir_tree/__init__.py
github_dir_tree/conf_temp
github_dir_tree/file_filter.py
github_dir_tree/generate_tree.py
github_dir_tree/get_option.py
github_dir_tree/main.py
github_dir_tree-1.1.0.dist-info/METADATA
github_dir_tree-1.1.0.dist-info/WHEEL
github_dir_tree-1.1.0.dist-info/top_level.txt
github_dir_tree-1.1.0.dist-info/RECORD
