Metadata-Version: 2.1
Name: github-dir-tree
Version: 1.1.0
Summary: github仓库目录树生成
Home-page: UNKNOWN
Author: Jefung
Author-email: 865424525@qq.com
License: MIT
Keywords: github dir_tree python
Platform: UNKNOWN
Classifier: Programming Language :: Python :: 3
Requires-Python: >=3
Requires-Dist: pathspec
